tamil_niral/__init__.py
tamil_niral/interpreter.py
tamil_niral-1.0.1.dist-info/licenses/LICENSE
tamil_niral-1.0.1.dist-info/METADATA
tamil_niral-1.0.1.dist-info/WHEEL
tamil_niral-1.0.1.dist-info/entry_points.txt
tamil_niral-1.0.1.dist-info/top_level.txt
tamil_niral-1.0.1.dist-info/RECORD
