Metadata-Version: 2.4
Name: tamil_niral
Version: 1.0.1
Summary: Tamil programming language 
Home-page: https://github.com/yourusername/tamil_niral
Author: Nithesh M
Requires-Python: >=3.7
License-File: LICENSE
Dynamic: author
Dynamic: description-content-type
Dynamic: home-page
Dynamic: license-file
Dynamic: requires-python
Dynamic: summary
